MANIFEST.in
README.md
setup.py
fix_sso_ui/__init__.py
fix_sso_ui/additional-info.json
fix_sso_ui/decorators.py
fix_sso_ui/utils.py
fix_sso_ui.egg-info/PKG-INFO
fix_sso_ui.egg-info/SOURCES.txt
fix_sso_ui.egg-info/dependency_links.txt
fix_sso_ui.egg-info/requires.txt
fix_sso_ui.egg-info/top_level.txt